{
	"noindex": true,
	"icon": "fa-redhat",
	"title": "OpenAPI Security",
	"time": "15 minutes",
	"difficulty": "Beginner",
	"description": "Introduction Security in OpenAPI",
	"details": {
		"steps": [{
				"title": "Setup",
				"text": "setup.md",
		    "code":"background.sh"
			},{
				"title": "Intro to Security Types",
				"text": "step1.md"
			},
			{
				"title": "Security Requirements Intro",
				"text": "step2.md"
			},
			{
				"title": "Update OpenAPI Spec",
				"text": "step3.md"
			},
			{
				"title": "Setup Security Realm",
				"text": "step4.md"
			},
			{
				"title": "Code Walkthrough",
				"text": "step5.md"
			},
			{
				"title": "Validate oAuth",
				"text": "step6.md"
			}
		],
		"intro": {
		  "title": "OpenAPI Security",
		  "text":"intro.md"
		}, "finish": {
		  "text": "finish.md"
		}
	},
	"environment": {
		"showide": true,
		"uiLayoutId": "editor-terminal",
		"uieditorpath": "/root/rhc_openapi_todo",
		"idePort": 23000,
		"dashboards": [{
			"name": "Swagger UI",
			"href": "https://[[HOST_SUBDOMAIN]]-8080-[[KATACODA_HOST]].environments.katacoda.com/swagger-ui.html"
		},{
			"name": "KeyCloak",
			"href": "https://[[HOST_SUBDOMAIN]]-8444-[[KATACODA_HOST]].environments.katacoda.com/"
		},{
			"name": "KeyCloak Unsecure",
			"href": "https://[[HOST_SUBDOMAIN]]-8081-[[KATACODA_HOST]].environments.katacoda.com/"
		}],

		"uilayout": "terminal-iframe"
	},
	"backend": {
		"imageid": "ubuntu",
		"port": 8080
	}
}
